brbug/__init__.py
brbug/__main__.py
brbug/brbug.py
brbug-0.1.1.1.dist-info/METADATA
brbug-0.1.1.1.dist-info/WHEEL
brbug-0.1.1.1.dist-info/entry_points.txt
brbug-0.1.1.1.dist-info/RECORD
