Metadata-Version: 2.1
Name: brbug
Version: 0.1.1.1
Summary: a tool/library to debug android BeeWare apps on Android with ease.
Home-page: https://github.com/matan-h/brbug
License: MIT
Keywords: beeware,android,debug,debuging,simple,easy,briefcase
Author: matan-h
Author-email: matan.honig2@gmail.com
Requires-Python: >=3.6,<4.0
Classifier: License :: OSI Approved :: MIT License
Classifier: Programming Language :: Python :: 3
Classifier: Programming Language :: Python :: 3.6
Classifier: Programming Language :: Python :: 3.7
Classifier: Programming Language :: Python :: 3.8
Classifier: Programming Language :: Python :: 3.9
Classifier: Programming Language :: Python :: 3.10
Classifier: Programming Language :: Python :: 3.11
Classifier: Programming Language :: Python :: 3.12
Provides-Extra: rich
Requires-Dist: click (>=8.1.7,<9.0.0)
Requires-Dist: executing (>=2.0.1,<3.0.0)
Requires-Dist: friendly-traceback (>=0.7.61,<0.8.0)
Requires-Dist: rich-click (>=1.7.2,<2.0.0) ; extra == "rich"
Requires-Dist: toml (>=0.10.2,<0.11.0)
Project-URL: issues, https://github.com/matan-h/brbug/issues
